infi.memuse-0.0.13-py2.7-nspkg.pth
infi/memuse/__init__.py
infi/memuse/__version__.py
infi/memuse/nose/__init__.py
infi.memuse-0.0.13.dist-info/DESCRIPTION.rst
infi.memuse-0.0.13.dist-info/METADATA
infi.memuse-0.0.13.dist-info/RECORD
infi.memuse-0.0.13.dist-info/WHEEL
infi.memuse-0.0.13.dist-info/entry_points.txt
infi.memuse-0.0.13.dist-info/metadata.json
infi.memuse-0.0.13.dist-info/namespace_packages.txt
infi.memuse-0.0.13.dist-info/top_level.txt
