Metadata-Version: 2.0
Name: infi.memuse
Version: 0.0.13
Summary: Nose plugin for testing for memory leaks during running tests
Home-page: https://github.com/Infinidat/infi.memuse
Author: Arnon Yaari
Author-email: arnony@infinidat.com
License: BSD
Platform: UNKNOWN
Classifier: Intended Audience :: Developers
Classifier: Intended Audience :: System Administrators
Classifier: License :: OSI Approved :: BSD License
Classifier: Operating System :: OS Independent
Classifier: Programming Language :: Python
Classifier: Topic :: Software Development :: Libraries :: Python Modules
Requires-Dist: infi.pyutils
Requires-Dist: psutil (>=1.2)
Requires-Dist: setuptools
